hindent/__init__.py
hindent-4.0.0.dist-info/LICENSE.md
hindent-4.0.0.dist-info/WHEEL
hindent-4.0.0.dist-info/METADATA
hindent-4.0.0.dist-info/RECORD
