Metadata-Version: 2.1
Name: hindent
Version: 4.0.0
Summary: Provides functions to translate and/or execute Hindent code.
Author-email: Grant Smith <14.gsmith.14@gmail.com>
Requires-Python: >=3.6
Classifier: Programming Language :: Python :: 3
Classifier: License :: OSI Approved :: MIT License
Classifier: Operating System :: OS Independent
Project-URL: home-page, https://github.com/GSmithApps/hindent
